cloud_cloner/__init__.py
cloud_cloner/__main__.py
cloud_cloner/bootstrap.py
cloud_cloner/clone.py
cloud_cloner/clone_directory.py
cloud_cloner/config.py
cloud_cloner/rclone_config.py
cloud_cloner/run.py
cloud_cloner-0.3.0.dist-info/entry_points.txt
cloud_cloner-0.3.0.dist-info/LICENSE.txt
cloud_cloner-0.3.0.dist-info/WHEEL
cloud_cloner-0.3.0.dist-info/METADATA
cloud_cloner-0.3.0.dist-info/RECORD
