Metadata-Version: 2.1
Name: cloud-cloner
Version: 0.3.0
Summary: Tool for cloning data from cloud storage services in a configurable way
License: MIT
Author: Omegastick
Requires-Python: >=3.9,<4.0
Classifier: License :: OSI Approved :: MIT License
Classifier: Programming Language :: Python :: 3
Classifier: Programming Language :: Python :: 3.9
Classifier: Programming Language :: Python :: 3.10
Classifier: Programming Language :: Python :: 3.11
Requires-Dist: dacite (>=1.6.0,<2.0.0)
Requires-Dist: python-rclone (>=0.0.2,<0.0.3)
Requires-Dist: pyyaml (>=6.0,<7.0)
Requires-Dist: typer[all] (>=0.7.0,<0.8.0)
